preset2lv2/__init__.py
preset2lv2/__main__.py
preset2lv2/dx7syx2lv2.py
preset2lv2/native2lv2.py
preset2lv2/v12lv2.py
preset2lv2/templates/manifest.ttl.tpl
preset2lv2/templates/preset.ttl.tpl
preset2lv2-0.1.3.dist-info/LICENSE
preset2lv2-0.1.3.dist-info/METADATA
preset2lv2-0.1.3.dist-info/WHEEL
preset2lv2-0.1.3.dist-info/entry_points.txt
preset2lv2-0.1.3.dist-info/top_level.txt
preset2lv2-0.1.3.dist-info/RECORD
