Metadata-Version: 2.1
Name: preset2lv2
Version: 0.1.3
Summary: Convert a set of native presets and generate a LV2 bundle containing one or more banks.
Home-page: https://gitlab.com/Jofemodo/synthv1-preset-converter
Author: Fernando Moyano
Author-email: fernando@zynthian.org
License: GNU General Public License v3 or later (GPLv3+)
Keywords: audio,plugin,lv2,dexed,synthv1,padthv1
Platform: UNKNOWN
Classifier: Programming Language :: Python :: 3
Classifier: License :: OSI Approved :: GNU General Public License v3 or later (GPLv3+)
Classifier: Operating System :: OS Independent
Requires-Dist: tornado (>=4)
Provides-Extra: rest
Requires-Dist: dxsyx ; extra == 'rest'
